power_profiler/__init__.py
power_profiler/__main__.py
power_profiler/power_profiler.py
power_profiler-0.3.0.dist-info/METADATA
power_profiler-0.3.0.dist-info/WHEEL
power_profiler-0.3.0.dist-info/entry_points.txt
power_profiler-0.3.0.dist-info/top_level.txt
power_profiler-0.3.0.dist-info/zip-safe
power_profiler-0.3.0.dist-info/RECORD
