Metadata-Version: 2.1
Name: power-profiler
Version: 0.3.0
Summary: A power profiling tool
Home-page: https://github.com/makerdiary/power-profiler
Author: Yihui Xiong
Author-email: yihui.xiong@hotmail.com
License: UNKNOWN
Platform: UNKNOWN
Requires-Dist: pyserial
Requires-Dist: pyqtgraph (>=0.11.0)
